{
 "actions": [],
 "allow_rename": 1,
 "autoname": "naming_series:",
 "creation": "2022-08-03 13:43:13.173347",
 "doctype": "DocType",
 "editable_grid": 1,
 "engine": "InnoDB",
 "field_order": [
  "installation_order",
  "installation_request",
  "installation_type",
  "column_break_3",
  "naming_series",
  "customer_info_section",
  "customer",
  "customer_name",
  "customer_phone_number",
  "column_break_24",
  "delegate",
  "delegate_name",
  "delegate_phone_number",
  "car_section_section",
  "car",
  "car_model",
  "column_break_17",
  "car_type",
  "car_brand",
  "accessories_section",
  "accessories_type",
  "accessories",
  "column_break_22",
  "accessories_warehouse",
  "accessories_name",
  "qty",
  "gps_details_section",
  "gps_type",
  "gps_item_code",
  "serial_number",
  "column_break_11",
  "gps_warehouse",
  "gps_no",
  "gps_series",
  "team_details_section",
  "team",
  "installation_team_detail",
  "engineer_name",
  "technical_name",
  "notes_section",
  "notes",
  "amended_from"
 ],
 "fields": [
  {
   "fieldname": "installation_order",
   "fieldtype": "Link",
   "label": "Installation Order",
   "mandatory_depends_on": "eval:doc.installation_type == \"New\"",
   "options": "Installation Order"
  },
  {
   "fieldname": "installation_type",
   "fieldtype": "Select",
   "in_list_view": 1,
   "label": "Installation Type",
   "options": "\nNew\nRenew",
   "reqd": 1
  },
  {
   "fieldname": "naming_series",
   "fieldtype": "Select",
   "in_list_view": 1,
   "label": "Series",
   "options": "INS-car-.",
   "reqd": 1
  },
  {
   "fieldname": "column_break_3",
   "fieldtype": "Column Break"
  },
  {
   "fieldname": "car",
   "fieldtype": "Link",
   "label": "Car",
   "options": "Car"
  },
  {
   "depends_on": "eval:doc.gps_type == 'Internal'",
   "fieldname": "serial_number",
   "fieldtype": "Link",
   "label": "Serial Number",
   "options": "Serial No"
  },
  {
   "fieldname": "car_section_section",
   "fieldtype": "Section Break",
   "label": "Car Details"
  },
  {
   "fieldname": "car_model",
   "fieldtype": "Data",
   "label": "Car Model"
  },
  {
   "fieldname": "car_type",
   "fieldtype": "Data",
   "label": "Car Type"
  },
  {
   "fieldname": "column_break_11",
   "fieldtype": "Column Break"
  },
  {
   "fieldname": "car_brand",
   "fieldtype": "Data",
   "label": "Car Brand"
  },
  {
   "fieldname": "customer_info_section",
   "fieldtype": "Section Break",
   "label": "Customer Info"
  },
  {
   "fieldname": "customer",
   "fieldtype": "Link",
   "label": "Customer",
   "options": "Customer"
  },
  {
   "fetch_from": "customer.customer_name",
   "fetch_if_empty": 1,
   "fieldname": "customer_name",
   "fieldtype": "Data",
   "label": "Customer Name",
   "read_only": 1
  },
  {
   "fieldname": "column_break_17",
   "fieldtype": "Column Break"
  },
  {
   "fieldname": "delegate",
   "fieldtype": "Link",
   "label": "Delegate",
   "options": "Customer Delegate"
  },
  {
   "fetch_from": "delegate.delegate_name",
   "fetch_if_empty": 1,
   "fieldname": "delegate_name",
   "fieldtype": "Data",
   "label": "Delegate Name",
   "read_only": 1
  },
  {
   "fieldname": "delegate_phone_number",
   "fieldtype": "Data",
   "label": "Delegate Phone Number"
  },
  {
   "fieldname": "customer_phone_number",
   "fieldtype": "Data",
   "label": "Phone Number"
  },
  {
   "depends_on": "eval:doc.accessories_type == \"Internal\"",
   "fieldname": "accessories",
   "fieldtype": "Link",
   "label": "Accessories",
   "options": "Item"
  },
  {
   "fieldname": "accessories_section",
   "fieldtype": "Section Break",
   "label": "Accessories Details"
  },
  {
   "depends_on": "eval:doc.accessories_type == \"Internal\"",
   "fieldname": "accessories_warehouse",
   "fieldtype": "Link",
   "label": "Accessories Warehouse",
   "options": "Warehouse"
  },
  {
   "fieldname": "qty",
   "fieldtype": "Data",
   "label": "QTY"
  },
  {
   "fieldname": "accessories_type",
   "fieldtype": "Select",
   "label": "Accessories Type",
   "options": "\nInternal\nExternal"
  },
  {
   "fetch_from": "accessories.item_name",
   "fetch_if_empty": 1,
   "fieldname": "accessories_name",
   "fieldtype": "Data",
   "label": "Accessories Name"
  },
  {
   "fieldname": "team_details_section",
   "fieldtype": "Section Break",
   "label": "Team Details"
  },
  {
   "fieldname": "installation_team_detail",
   "fieldtype": "Table",
   "label": "Installation Team Detail",
   "options": "Installation Team Detail"
  },
  {
   "fieldname": "gps_details_section",
   "fieldtype": "Section Break",
   "label": "GPS Details"
  },
  {
   "fieldname": "column_break_24",
   "fieldtype": "Column Break"
  },
  {
   "fieldname": "gps_no",
   "fieldtype": "Data",
   "label": "GPS No"
  },
  {
   "fieldname": "gps_series",
   "fieldtype": "Data",
   "label": "GPS Series"
  },
  {
   "fieldname": "engineer_name",
   "fieldtype": "Data",
   "label": "Engineer Name"
  },
  {
   "fieldname": "technical_name",
   "fieldtype": "Data",
   "label": "Technical Name"
  },
  {
   "fieldname": "gps_type",
   "fieldtype": "Select",
   "label": "GPS Type",
   "options": "\nInternal\nExternal"
  },
  {
   "fieldname": "team",
   "fieldtype": "Link",
   "label": "Team",
   "options": "Installation Team"
  },
  {
   "depends_on": "eval:doc.gps_type == 'Internal'",
   "fieldname": "gps_warehouse",
   "fieldtype": "Link",
   "label": "GPS Warehouse",
   "options": "Warehouse"
  },
  {
   "fieldname": "column_break_22",
   "fieldtype": "Column Break"
  },
  {
   "fieldname": "gps_item_code",
   "fieldtype": "Link",
   "label": "GPS Item Code",
   "options": "Item"
  },
  {
   "fieldname": "notes_section",
   "fieldtype": "Section Break",
   "label": "Notes"
  },
  {
   "fieldname": "notes",
   "fieldtype": "Text",
   "label": "Notes"
  },
  {
   "fieldname": "amended_from",
   "fieldtype": "Link",
   "label": "Amended From",
   "no_copy": 1,
   "options": "Car Installation",
   "print_hide": 1,
   "read_only": 1
  },
  {
   "fetch_from": "installation_order.installation_request",
   "fieldname": "installation_request",
   "fieldtype": "Link",
   "in_filter": 1,
   "label": "Installation Request",
   "options": "Installation Request",
   "read_only": 1
  }
 ],
 "index_web_pages_for_search": 1,
 "is_submittable": 1,
 "links": [],
 "modified": "2022-08-04 11:04:31.338665",
 "modified_by": "Administrator",
 "module": "Hardware Installations",
 "name": "Car Installation",
 "owner": "Administrator",
 "permissions": [
  {
   "create": 1,
   "delete": 1,
   "email": 1,
   "export": 1,
   "print": 1,
   "read": 1,
   "report": 1,
   "role": "System Manager",
   "share": 1,
   "write": 1
  }
 ],
 "sort_field": "modified",
 "sort_order": "DESC"
}